{
  "url": "http://ufcstats.com/fighter-details/d66a46de8d705353",
  "stats": {
    "name": "Jeremiah Wells",
    "record": "13-4-1",
    "wins": 13,
    "losses": 4,
    "draws": 1,
    "height": "5' 9\"",
    "weight": "170 lbs.",
    "reach": "74\"",
    "stance": "Switch",
    "dob": "Oct 30, 1986",
    "strikes_landed_per_min": 2.35,
    "striking_accuracy": null,
    "strikes_absorbed_per_min": 1.28,
    "striking_defense": 0.48,
    "takedown_average": null,
    "takedown_accuracy": 0.46,
    "takedown_defense": 0.5,
    "submission_average": null
  },
  "fight_history": [
    {
      "opponent": "Themba Gorimbo",
      "result": "win",
      "date": "Nov. 01, 2025",
      "method": "N/A"
    },
    {
      "opponent": "Max Griffin",
      "result": "loss",
      "date": "Feb. 10, 2024",
      "method": "N/A"
    },
    {
      "opponent": "Carlston Harris",
      "result": "loss",
      "date": "Aug. 05, 2023",
      "method": "Submission (Anaconda Choke)"
    },
    {
      "opponent": "Matthew Semelsberger",
      "result": "win",
      "date": "Apr. 22, 2023",
      "method": "N/A"
    },
    {
      "opponent": "Court McGee",
      "result": "win",
      "date": "Jun. 18, 2022",
      "method": "KO/TKO (Punch)"
    },
    {
      "opponent": "Blood Diamond",
      "result": "win",
      "date": "Feb. 12, 2022",
      "method": "Submission (Rear Naked Choke)"
    },
    {
      "opponent": "Warlley Alves",
      "result": "win",
      "date": "Jun. 26, 2021",
      "method": "KO/TKO (Punch)"
    }
  ]
}